simplygame/__init__.py
simplygame/main.py
simplygame/simplygame.py
simplygame-1.0.7.dist-info/METADATA
simplygame-1.0.7.dist-info/WHEEL
simplygame-1.0.7.dist-info/top_level.txt
simplygame-1.0.7.dist-info/RECORD
