Metadata-Version: 2.2
Name: simplygame
Version: 1.0.7
Summary: A package to create games more easily
Home-page: https://github.com/cedzeedev/simplygame
Author: CEDZEE
Author-email: cedzee.contact@gmail.com
Classifier: Programming Language :: Python :: 3
Classifier: License :: OSI Approved :: MIT License
Classifier: Operating System :: OS Independent
Classifier: Topic :: Games/Entertainment
Classifier: Intended Audience :: Developers
Requires-Python: >=3.10
Requires-Dist: pygame
Dynamic: author
Dynamic: author-email
Dynamic: classifier
Dynamic: description
Dynamic: description-content-type
Dynamic: home-page
Dynamic: requires-dist
Dynamic: requires-python
Dynamic: summary
